[
    {
        "name": "mfebb002",
        "id": "stationUser-1cf1129a-248b-4393-9a56-64a6a15d36c4",
        "bay_id": "S-70:b3:d5:8f:92:ff-00000000898cee65_B-8"
    },
    {
        "name": "mfebb002",
        "id": "stationUser-1cf1129a-248b-4393-9a56-64a6a15d36c4",
        "bay_id": "S-70:b3:d5:8f:92:ff-00000000898cee65_B-8"
    },
    {
        "name": "mfebb002",
        "id": "stationUser-1cf1129a-248b-4393-9a56-64a6a15d36c4",
        "bay_id": "S-70:b3:d5:8f:92:ff-00000000898cee65_B-8"
    },
    {
        "name": "mfebb002",
        "id": "stationUser-1cf1129a-248b-4393-9a56-64a6a15d36c4",
        "bay_id": "S-70:b3:d5:8f:92:ff-00000000898cee65_B-8"
    }
]